rtfilter/butterworth.py
rtfilter/core/core_butterworth.py
rtfilter/core/filter_types.py
rtfilter-0.1.0.dist-info/LICENSE
rtfilter-0.1.0.dist-info/METADATA
rtfilter-0.1.0.dist-info/WHEEL
rtfilter-0.1.0.dist-info/RECORD
