Metadata-Version: 2.3
Name: rtfilter
Version: 0.1.0
Summary: Real-time filters for signal processing.
License: GPL-3.0 license
Author: Dominik I. Braun
Author-email: dome.braun@fau.de
Requires-Python: >=3.10,<4.0
Classifier: License :: Other/Proprietary License
Classifier: Programming Language :: Python :: 3
Classifier: Programming Language :: Python :: 3.10
Classifier: Programming Language :: Python :: 3.11
Classifier: Programming Language :: Python :: 3.12
Classifier: Programming Language :: Python :: 3.13
Requires-Dist: scipy (>=1.14.1,<2.0.0)
